pydoc_mintlify/__init__.py
pydoc_mintlify/cli.py
pydoc_mintlify/mintlify_renderer.py
pydoc_mintlify-0.1.2.dist-info/METADATA
pydoc_mintlify-0.1.2.dist-info/WHEEL
pydoc_mintlify-0.1.2.dist-info/entry_points.txt
pydoc_mintlify-0.1.2.dist-info/licenses/LICENSE
pydoc_mintlify-0.1.2.dist-info/RECORD
