Metadata-Version: 2.4
Name: pydoc-mintlify
Version: 0.1.2
Summary: pydoc-markdown plugin for Mintlify, auto-generate mintlify docs from your python docstrings
Project-URL: Homepage, https://github.com/TyTodd/pydoc-mintlify
License-File: LICENSE
Requires-Python: >=3.9
Requires-Dist: pydoc-markdown>=4.8.2
Requires-Dist: typer>=0.14.0
Requires-Dist: watchfiles>=1.1.1
